web_novel_scrapper/__init__.py
web_novel_scrapper/__main__.py
web_novel_scrapper/decode.py
web_novel_scrapper/file_manager.py
web_novel_scrapper/logger_manager.py
web_novel_scrapper/novel_scrapper.py
web_novel_scrapper/request_manager.py
web_novel_scrapper/utils.py
web_novel_scrapper/version.py
web_novel_scrapper/decode_guide/decode_guide.json
web_novel_scrapper-1.0.1.dist-info/METADATA
web_novel_scrapper-1.0.1.dist-info/WHEEL
web_novel_scrapper-1.0.1.dist-info/entry_points.txt
web_novel_scrapper-1.0.1.dist-info/RECORD
