Metadata-Version: 2.4
Name: web-novel-scrapper
Version: 1.0.1
Summary: Python tool that allows you to scrape web novels from various sources and save them to more readable formats like EPUB.
Project-URL: Homepage, https://github.com/ImagineBrkr/web-novel-scrapper
Project-URL: Repository, https://github.com/ImagineBrkr/web-novel-scrapper.git
Author-email: ImagineBrkr <salvattore_25@hotmail.com>
Keywords: Novel Downloader,Scrapper,Web Novel,Web Novel Downloader,Web Novel Scrapper
Requires-Python: >=3.10
Requires-Dist: bs4>=0.0.2
Requires-Dist: click<8,>=7.0
Requires-Dist: dataclasses-json<1,>=0.6.7
Requires-Dist: ebooklib<1,>=0.18
Requires-Dist: platformdirs
Requires-Dist: python-dotenv
Requires-Dist: requests
